miniomni/__init__.py
miniomni/clock/__init__.py
miniomni/clock/clock.py
miniomni/clock/mini_profile.py
miniomni/seed/__init__.py
miniomni/seed/seed.py
miniomni-0.0.3.dist-info/METADATA
miniomni-0.0.3.dist-info/WHEEL
miniomni-0.0.3.dist-info/top_level.txt
miniomni-0.0.3.dist-info/RECORD
