Metadata-Version: 2.4
Name: miniomni
Version: 0.0.3
Summary: A universal utility toolkit by minipuding
Author: minipuding
License: MIT
Requires-Python: >=3.8
